MANIFEST.in
setup.py
angel_worker/__init__.py
angel_worker/authority.py
angel_worker/constants.py
angel_worker/executor.py
angel_worker/heartbeat.py
angel_worker/log_collector.py
angel_worker/pull.py
angel_worker/worker.py
angel_worker.egg-info/PKG-INFO
angel_worker.egg-info/SOURCES.txt
angel_worker.egg-info/dependency_links.txt
angel_worker.egg-info/entry_points.txt
angel_worker.egg-info/not-zip-safe
angel_worker.egg-info/requires.txt
angel_worker.egg-info/top_level.txt
angel_worker/api/__init__.py
angel_worker/api/response.py
angel_worker/api/rpc_service.py
angel_worker/core/__init__.py
angel_worker/core/config_util.py
angel_worker/core/ftp_client.py
angel_worker/core/tail.py
etc/logger.conf
etc/worker.conf
examples/simple_register.py
examples/simple_start.py
examples/.cache/v/cache/lastfailed
scripts/register_worker
scripts/worker_daemon
tests/test_ftp_client.py
tests/.cache/v/cache/lastfailed
tests/tmp/file0
tests/tmp/test_download
tests/tmp/dir0/file0
tests/tmp/dir0/test_upload