Metadata-Version: 1.1
Name: angel-worker
Version: 1.0.9
Summary: The worker of a distribute job scheduler named 'angel'
Home-page: https://pypi.python.org/pypi/angel_worker
Author: Lafite93
Author-email: 2273337844@qq.com
License: Apache
Keywords: angel worker executor
Platform: Linux
Platform: Unix
Classifier: Programming Language :: Python :: 3
Classifier: Programming Language :: Python :: 3.5
